{
  "params": {
    "weights": {
      "VANGUARD": 0.236,
      "ORION": 0.327,
      "HELIOS": 0.185,
      "QUANTUM": 0.152,
      "CRYPTO": 0.101
    },
    "target_vol": 0.15,
    "vol_cap": 1.0,
    "vol_floor": 0.25,
    "vol_win": 60,
    "dd_floor": -0.1,
    "dd_win": 252,
    "vol_gate_pct": 0.99,
    "tc_bps_per_lev_chg": 10.0
  },
  "full": {
    "sharpe": 2.3657,
    "sortino": 3.5094,
    "cagr": 0.3725,
    "vol": 0.138,
    "mdd": -0.1765,
    "calmar": 2.1101,
    "navx": 204.9181,
    "n": 4236
  },
  "is": {
    "sharpe": 2.5577,
    "sortino": 3.8638,
    "cagr": 0.3822,
    "vol": 0.1299,
    "mdd": -0.1632,
    "calmar": 2.3423,
    "navx": 19.137,
    "n": 2298
  },
  "oos": {
    "sharpe": 2.1735,
    "sortino": 3.2009,
    "cagr": 0.3613,
    "vol": 0.147,
    "mdd": -0.1765,
    "calmar": 2.0468,
    "navx": 10.708,
    "n": 1937
  },
  "is_oos_gap": 0.3842,
  "avg_total_mult": 0.8522763143359892,
  "avg_vol_target_mult": 0.8918291744146387,
  "correlations": {
    "VANGUARD": {
      "VANGUARD": 1.0,
      "ORION": -0.017,
      "HELIOS": -0.048,
      "QUANTUM": 0.039,
      "CRYPTO": 0.129
    },
    "ORION": {
      "VANGUARD": -0.017,
      "ORION": 1.0,
      "HELIOS": -0.016,
      "QUANTUM": 0.184,
      "CRYPTO": 0.0
    },
    "HELIOS": {
      "VANGUARD": -0.048,
      "ORION": -0.016,
      "HELIOS": 1.0,
      "QUANTUM": -0.036,
      "CRYPTO": 0.016
    },
    "QUANTUM": {
      "VANGUARD": 0.039,
      "ORION": 0.184,
      "HELIOS": -0.036,
      "QUANTUM": 1.0,
      "CRYPTO": 0.005
    },
    "CRYPTO": {
      "VANGUARD": 0.129,
      "ORION": 0.0,
      "HELIOS": 0.016,
      "QUANTUM": 0.005,
      "CRYPTO": 1.0
    }
  }
}